{"pL": 9.26, "pReceita(psr)": 2.01, "pVp": 1.24, "dividendYieldAgro3": 0.1351, "payout": 1.2515, "margemLiquida": 0.2172, "margemBruta": 0.2937, "margemEbit": 0.1866, "margemEbitda": 0.2823, "evEbitda": 9.54, "evEbit": 14.44, "pEbitda": 7.13, "pEbit": 10.78, "pAtivo": 0.74, "pCapgiro": 4.01, "pAtivoCircLiq": -1.12, "vpa": 19.24, "lpa": 2.57, "giroAtivos": 0.37, "roe": 0.1334, "roic": 0.0739, "roa": 0.0803, "dividaLiquidaPatrimonio": 0.42, "dividaLiquidaEbitda": 2.42, "dividaLiquidaEbit": 3.66, "dividaBrutaPatrimonio": 0.53, "patrimonioAtivos": 0.6, "passivosAtivos": 0.4, "liquidezCorrente": 2.25, "cagrReceitas5Anos": 0.1641, "cagrLucros5Anos": 0.2093, "valorDeMercado": 2440785000.0, "valorDeFirma": 3268619000.0, "patrimonioLiquido": 1976036000.0, "noTotalDePapeis": 102683000.0, "ativos": 3282201000.0, "ativoCirculante": 1096135000.0, "dividaBruta": 1047917000.0, "dividaLiquida": 827834000.0, "disponibilidade": 220083000.0, "segmentoDeListagem": "Novo Mercado", "freeFloat": 0.6211, "tagAlong": 1.0, "liquidezMediaDiaria": 8088000.0, "setor": "Consumo n\u00e3o C\u00edclico", "segmento": "Agricultura", "date": 1708204034.039806}