{"pL": -0.31, "pReceita(psr)": 0.08, "pVp": 1.73, "dividendYieldAmar3": 0.0, "payout": 0.0, "margemLiquida": -0.2668, "margemBruta": 0.3553, "margemEbit": -0.1635, "margemEbitda": -0.1398, "evEbitda": -4.15, "evEbit": -3.55, "pEbitda": -0.6, "pEbit": -0.51, "pAtivo": 0.08, "pCapgiro": -0.57, "pAtivoCircLiq": -0.12, "vpa": 1.57, "lpa": -8.71, "giroAtivos": 0.9, "roe": -5.5409, "roic": -0.2715, "roa": -0.2409, "dividaLiquidaPatrimonio": 10.33, "dividaLiquidaEbitda": -3.56, "dividaLiquidaEbit": -3.04, "dividaBrutaPatrimonio": 12.27, "patrimonioAtivos": 0.04, "passivosAtivos": 0.96, "liquidezCorrente": 0.75, "cagrReceitas5Anos": -0.0493, "valorDeMercado": 186506000.0, "valorDeFirma": 1299668000.0, "patrimonioLiquido": 107804000.0, "noTotalDePapeis": 68568000.0, "ativos": 2479688000.0, "ativoCirculante": 978950000.0, "dividaBruta": 1323245000.0, "dividaLiquida": 1113162000.0, "disponibilidade": 210083000.0, "segmentoDeListagem": "Novo Mercado", "freeFloat": 0.4566, "tagAlong": 1.0, "liquidezMediaDiaria": 1011000.0, "setor": "Consumo C\u00edclico", "segmento": "Tecidos . Vestu\u00e1rio e Cal\u00e7ados", "date": 1708203126.387866}