{"pL": 0.52, "pReceita(psr)": 0.21, "pVp": 38.23, "dividendYieldAtmp3": 0.0, "payout": 0.0, "margemLiquida": 0.3988, "margemBruta": -0.2248, "margemEbit": -0.4686, "margemEbitda": -0.1751, "evEbitda": -4.89, "evEbit": -1.83, "pEbitda": -1.18, "pEbit": -0.44, "pAtivo": 0.06, "pCapgiro": 5.44, "pAtivoCircLiq": -0.07, "vpa": 0.08, "lpa": 6.21, "giroAtivos": 0.27, "roe": 73.7644, "roic": -0.5901, "roa": 0.1072, "dividaLiquidaPatrimonio": 120.22, "dividaLiquidaEbitda": -3.71, "dividaLiquidaEbit": -1.39, "dividaBrutaPatrimonio": 145.87, "patrimonioAtivos": 0.0, "passivosAtivos": 1.0, "liquidezCorrente": 1.05, "cagrReceitas5Anos": -0.2109, "valorDeMercado": "R$ 86.007.000", "valorDeFirma": "R$ 356.492.000", "patrimonioLiquido": "R$ 2.250.000", "noTotalDePapeis": 26710000.0, "ativos": "R$ 1.547.645.000", "ativoCirculante": "R$ 358.055.000", "dividaBruta": "R$ 328.212.000", "dividaLiquida": "R$ 270.485.000", "disponibilidade": "R$ 57.727.000", "segmentoDeListagem": "Novo Mercado", "freeFloat": 0.2869, "tagAlong": 1.0, "liquidezMediaDiaria": "R$ 3.195.000", "setor": "Bens Industriais", "segmento": "Servi\u00e7os Diversos"}