{"pL": 11.58, "pReceita(psr)": 0.15, "pVp": 6.73, "dividendYieldBeef3": 0.0792, "payout": 0.1964, "margemLiquida": 0.0132, "margemBruta": 0.1988, "margemEbit": 0.0742, "margemEbitda": 0.093, "evEbitda": 5.14, "evEbit": 6.45, "pEbitda": 1.65, "pEbit": 2.07, "pAtivo": 0.16, "pCapgiro": 0.6, "pAtivoCircLiq": -0.39, "vpa": 1.03, "lpa": 0.6, "giroAtivos": 1.06, "roe": 0.5814, "roic": 0.0963, "roa": 0.0135, "dividaLiquidaPatrimonio": 14.28, "dividaLiquidaEbitda": 3.5, "dividaLiquidaEbit": 4.38, "dividaBrutaPatrimonio": 30.93, "patrimonioAtivos": 0.02, "passivosAtivos": 0.96, "liquidezCorrente": 1.87, "cagrReceitas5Anos": 0.112, "valorDeMercado": "R$ 4.226.692.000", "valorDeFirma": "R$ 13.191.129.000", "patrimonioLiquido": "R$ 627.948.000", "noTotalDePapeis": 607283000.0, "ativos": "R$ 25.906.758.000", "ativoCirculante": "R$ 15.167.947.000", "dividaBruta": "R$ 19.421.731.000", "dividaLiquida": "R$ 8.964.437.000", "disponibilidade": "R$ 10.457.294.000", "segmentoDeListagem": "Novo Mercado", "freeFloat": 0.4287, "tagAlong": 1.0, "liquidezMediaDiaria": "R$ 76.787.000", "setor": "Consumo n\u00e3o C\u00edclico", "segmento": "Carnes e Derivados"}