{"pL": 9.17, "pReceita(psr)": 2.15, "pVp": 1.47, "dividendYieldBlau3": 0.0298, "payout": 0.3165, "margemLiquida": 0.2341, "margemBruta": 0.3936, "margemEbit": 0.1198, "margemEbitda": 0.1436, "evEbitda": 15.61, "evEbit": 18.71, "pEbitda": 14.94, "pEbit": 17.91, "pAtivo": 0.94, "pCapgiro": 2.51, "pAtivoCircLiq": -2.0, "vpa": 11.01, "lpa": 1.76, "giroAtivos": 0.44, "roe": 0.1603, "roic": 0.024, "roa": 0.1021, "dividaLiquidaPatrimonio": 0.07, "dividaLiquidaEbitda": 0.67, "dividaLiquidaEbit": 0.81, "dividaBrutaPatrimonio": 0.31, "patrimonioAtivos": 0.64, "passivosAtivos": 0.36, "liquidezCorrente": 3.44, "cagrReceitas5Anos": 0.1163, "cagrLucros5Anos": 0.1983, "valorDeMercado": "R$ 2.900.800.000", "valorDeFirma": "R$ 3.031.408.000", "patrimonioLiquido": "R$ 1.974.821.000", "noTotalDePapeis": 179393000.0, "ativos": "R$ 3.074.044.000", "ativoCirculante": "R$ 1.626.550.000", "dividaBruta": "R$ 602.548.000", "dividaLiquida": "R$ 130.608.000", "disponibilidade": "R$ 471.940.000", "segmentoDeListagem": "N\u00edvel 1", "freeFloat": 0.1663, "tagAlong": 1.0, "liquidezMediaDiaria": "R$ 15.450.000", "setor": "Sa\u00fade", "segmento": "Servi\u00e7os M\u00e9dicos, Hospitalares, An\u00e1lises e Diagn\u00f3sticos"}