{"pL": 5.5, "pReceita(psr)": 1.02, "pVp": 0.9, "dividendYieldCsmg3": 0.0893, "payout": 0.2534, "margemLiquida": 0.1847, "margemBruta": 0.4021, "margemEbit": 0.2361, "margemEbitda": 0.3471, "evEbitda": 4.3, "evEbit": 6.33, "pEbitda": 2.93, "pEbit": 4.3, "pAtivo": 0.51, "pCapgiro": 7.11, "pAtivoCircLiq": -0.63, "vpa": 20.75, "lpa": 3.4, "giroAtivos": 0.5, "roe": 0.1638, "roic": 0.1082, "roa": 0.0922, "dividaLiquidaPatrimonio": 0.42, "dividaLiquidaEbitda": 1.38, "dividaLiquidaEbit": 2.03, "dividaBrutaPatrimonio": 0.58, "patrimonioAtivos": 0.56, "passivosAtivos": 0.44, "liquidezCorrente": 1.58, "cagrReceitas5Anos": 0.0811, "cagrLucros5Anos": 0.1743, "valorDeMercado": "R$ 7.110.732.000", "valorDeFirma": "R$ 10.456.430.000", "patrimonioLiquido": "R$ 7.891.106.000", "noTotalDePapeis": 380253000.0, "ativos": "R$ 14.016.273.000", "ativoCirculante": "R$ 2.715.478.000", "dividaBruta": "R$ 4.596.548.000", "dividaLiquida": "R$ 3.345.698.000", "disponibilidade": "R$ 1.250.850.000", "segmentoDeListagem": "Novo Mercado", "freeFloat": 0.4956, "tagAlong": 1.0, "liquidezMediaDiaria": "R$ 35.920.000", "setor": "Utilidade P\u00fablica", "segmento": "\u00c1gua e Saneamento"}