{"pL": 9.35, "pReceita(psr)": 1.51, "pVp": 1.96, "dividendYieldCsud3": 0.051, "payout": 0.4303, "margemLiquida": 0.162, "margemBruta": 0.392, "margemEbit": 0.2127, "margemEbitda": 0.33, "evEbitda": 4.55, "evEbit": 7.07, "pEbitda": 4.59, "pEbit": 7.12, "pAtivo": 1.32, "pCapgiro": 20.7, "pAtivoCircLiq": -1.84, "vpa": 9.87, "lpa": 2.07, "giroAtivos": 0.87, "roe": 0.2092, "roic": 0.1783, "roa": 0.1416, "dividaLiquidaPatrimonio": -0.01, "dividaLiquidaEbitda": -0.03, "dividaLiquidaEbit": -0.05, "dividaBrutaPatrimonio": 0.18, "patrimonioAtivos": 0.68, "passivosAtivos": 0.32, "liquidezCorrente": 1.29, "cagrReceitas5Anos": 0.0489, "cagrLucros5Anos": 0.2137, "valorDeMercado": "R$ 807.158.000", "valorDeFirma": "R$ 801.140.000", "patrimonioLiquido": "R$ 412.720.000", "noTotalDePapeis": 41800000.0, "ativos": "R$ 609.916.000", "ativoCirculante": "R$ 171.969.000", "dividaBruta": "R$ 73.156.000", "dividaLiquida": "R$ -6.018.000", "disponibilidade": "R$ 79.174.000", "segmentoDeListagem": "Novo Mercado", "freeFloat": 0.4426, "tagAlong": 1.0, "liquidezMediaDiaria": "R$ 4.500.000", "setor": "Bens Industriais", "segmento": "Servi\u00e7os Diversos"}