{"pL": 7.11, "pReceita(psr)": 1.74, "pVp": 1.14, "dividendYieldGepa4": 0.077, "payout": 0.5183, "margemLiquida": 0.2445, "margemBruta": 0.4267, "margemEbit": 0.3735, "margemEbitda": 0.5664, "evEbitda": 3.7, "evEbit": 5.62, "pEbitda": 3.07, "pEbit": 4.65, "pAtivo": 0.68, "pCapgiro": -6.08, "pAtivoCircLiq": -0.79, "vpa": 22.48, "lpa": 3.61, "giroAtivos": 0.39, "roe": 0.1606, "roic": 0.1362, "roa": 0.0961, "dividaLiquidaPatrimonio": 0.22, "dividaLiquidaEbitda": 0.59, "dividaLiquidaEbit": 0.89, "dividaBrutaPatrimonio": 0.35, "patrimonioAtivos": 0.6, "passivosAtivos": 0.4, "liquidezCorrente": 0.54, "cagrReceitas5Anos": 0.0019, "cagrLucros5Anos": 0.0672, "valorDeMercado": 2465023000.0, "valorDeFirma": 2927432000.0, "patrimonioLiquido": 2123240000.0, "noTotalDePapeis": 94433000.0, "ativos": 3550141000.0, "ativoCirculante": 466948000.0, "dividaBruta": 734374000.0, "dividaLiquida": 462409000.0, "disponibilidade": 271965000.0, "segmentoDeListagem": "Tradicional", "freeFloat": 0.0381, "tagAlong": 0, "liquidezMediaDiaria": 16000.0, "setor": "Utilidade P\u00fablica", "segmento": "Energia El\u00e9trica", "date": 1708203773.789773}