{"pL": 12.75, "pReceita(psr)": 1.6, "pVp": 2.69, "dividendYieldIntb3": 0.0282, "payout": 0.3236, "margemLiquida": 0.1253, "margemBruta": 0.3146, "margemEbit": 0.1178, "margemEbitda": 0.1344, "evEbitda": 11.41, "evEbit": 13.02, "pEbitda": 11.89, "pEbit": 13.56, "pAtivo": 1.41, "pCapgiro": 3.09, "pAtivoCircLiq": -5.15, "vpa": 7.53, "lpa": 1.59, "giroAtivos": 0.88, "roe": 0.211, "roic": 0.1332, "roa": 0.1106, "dividaLiquidaPatrimonio": -0.11, "dividaLiquidaEbitda": -0.48, "dividaLiquidaEbit": -0.54, "dividaBrutaPatrimonio": 0.38, "patrimonioAtivos": 0.52, "passivosAtivos": 0.47, "liquidezCorrente": 2.68, "valorDeMercado": "R$ 6.643.953.000", "valorDeFirma": "R$ 6.378.197.000", "patrimonioLiquido": "R$ 2.468.362.000", "noTotalDePapeis": 327611000.0, "ativos": "R$ 4.720.396.000", "ativoCirculante": "R$ 3.431.024.000", "dividaBruta": "R$ 936.160.000", "dividaLiquida": "R$ -265.756.000", "disponibilidade": "R$ 1.201.916.000", "segmentoDeListagem": "Novo Mercado", "freeFloat": 0.3497, "tagAlong": 1.0, "liquidezMediaDiaria": "R$ 31.253.000", "setor": "Telecomunica\u00e7\u00f5es", "segmento": "Telecomunica\u00e7\u00f5es"}