{"pL": 5.38, "pVp": 3.12, "dividendYieldMoar3": 0.0046, "payout": 1.5296, "margemLiquida": 0.0, "margemBruta": 0.0, "margemEbit": 0.0, "margemEbitda": 0.0, "evEbit": 3.59, "pEbit": 4.07, "pAtivo": 1.47, "pCapgiro": 3.75, "pAtivoCircLiq": -3.15, "vpa": 124.41, "lpa": 72.18, "giroAtivos": 0.0, "roe": 0.5802, "roic": 0.3593, "roa": 0.4249, "dividaLiquidaPatrimonio": -0.37, "dividaLiquidaEbit": -0.48, "dividaBrutaPatrimonio": 0.71, "patrimonioAtivos": 0.47, "passivosAtivos": 0.53, "liquidezCorrente": 3.76, "cagrReceitas5Anos": -1.0, "cagrLucros5Anos": 0.9817, "valorDeMercado": "R$ 4.753.475.000", "valorDeFirma": "R$ 4.187.475.000", "patrimonioLiquido": "R$ 1.524.140.000", "noTotalDePapeis": 12251000.0, "ativos": "R$ 3.235.480.000", "ativoCirculante": "R$ 1.724.926.000", "dividaBruta": "R$ 1.085.837.000", "dividaLiquida": "R$ -566.000.000", "disponibilidade": "R$ 1.651.837.000", "segmentoDeListagem": "Tradicional", "freeFloat": 0.0221, "tagAlong": 0, "liquidezMediaDiaria": "R$ 325.000", "setor": "Financeiro", "segmento": "Holdings Diversificadas"}