{"pL": -28.56, "pReceita(psr)": 3.99, "pVp": 4.9, "dividendYieldOrvr3": 0.0, "payout": 0.0, "margemLiquida": -0.1399, "margemBruta": 0.3063, "margemEbit": 0.1755, "margemEbitda": 0.4066, "evEbitda": 12.89, "evEbit": 29.87, "pEbitda": 9.82, "pEbit": 22.76, "pAtivo": 1.35, "pCapgiro": 9.08, "pAtivoCircLiq": -1.85, "vpa": 7.44, "lpa": -1.28, "giroAtivos": 0.34, "roe": -0.1714, "roic": 0.0573, "roa": -0.0438, "dividaLiquidaPatrimonio": 1.53, "dividaLiquidaEbitda": 3.07, "dividaLiquidaEbit": 7.11, "dividaBrutaPatrimonio": 1.85, "patrimonioAtivos": 0.28, "passivosAtivos": 0.7, "liquidezCorrente": 2.22, "valorDeMercado": "R$ 3.023.559.000", "valorDeFirma": "R$ 3.967.420.000", "patrimonioLiquido": "R$ 617.519.000", "noTotalDePapeis": 82950000.0, "ativos": "R$ 2.239.121.000", "ativoCirculante": "R$ 606.045.000", "dividaBruta": "R$ 1.144.658.000", "dividaLiquida": "R$ 943.861.000", "disponibilidade": "R$ 200.797.000", "segmentoDeListagem": "N\u00edvel 1", "freeFloat": 0.5102, "tagAlong": 1.0, "liquidezMediaDiaria": "R$ 7.236.000", "setor": "Sa\u00fade", "segmento": "Servi\u00e7os M\u00e9dicos, Hospitalares, An\u00e1lises e Diagn\u00f3sticos"}