{"pL": 9.84, "pReceita(psr)": 1.22, "pVp": 2.33, "dividendYieldPomo4": 0.0401, "payout": 0.5633, "margemLiquida": 0.1241, "margemBruta": 0.2168, "margemEbit": 0.1116, "margemEbitda": 0.136, "evEbitda": 9.38, "evEbit": 11.44, "pEbitda": 8.97, "pEbit": 10.94, "pAtivo": 1.03, "pCapgiro": 3.17, "pAtivoCircLiq": -2.61, "vpa": 3.56, "lpa": 0.84, "giroAtivos": 0.84, "roe": 0.2364, "roic": 0.1036, "roa": 0.1056, "dividaLiquidaPatrimonio": 0.31, "dividaLiquidaEbitda": 1.18, "dividaLiquidaEbit": 1.44, "dividaBrutaPatrimonio": 0.73, "patrimonioAtivos": 0.44, "passivosAtivos": 0.55, "liquidezCorrente": 2.16, "cagrReceitas5Anos": 0.0828, "cagrLucros5Anos": 0.3054, "valorDeMercado": 7163854000.0, "valorDeFirma": 8196925000.0, "patrimonioLiquido": 3369746000.0, "noTotalDePapeis": 946892000.0, "ativos": 7613294000.0, "ativoCirculante": 4614025000.0, "dividaBruta": 2464319000.0, "dividaLiquida": 1033071000.0, "disponibilidade": 1431248000.0, "segmentoDeListagem": "N\u00edvel 2", "freeFloat": 0.7623, "tagAlong": 0.8, "liquidezMediaDiaria": 57917000.0, "setor": "Bens Industriais", "segmento": "Material Rodovi\u00e1rio", "date": 1708204064.9131541}