{"pL": 31.62, "pReceita(psr)": 3.61, "pVp": 3.04, "dividendYieldSmft3": 0.0186, "payout": 0.5879, "margemLiquida": 0.1141, "margemBruta": 0.3924, "margemEbit": 0.2439, "margemEbitda": 0.4771, "evEbitda": 7.93, "evEbit": 15.5, "pEbitda": 7.56, "pEbit": 14.78, "pAtivo": 1.08, "pCapgiro": 12.97, "pAtivoCircLiq": -1.47, "vpa": 8.04, "lpa": 0.77, "giroAtivos": 0.3, "roe": 0.096, "roic": 0.1092, "roa": 0.0348, "dividaLiquidaPatrimonio": 0.15, "dividaLiquidaEbitda": 0.37, "dividaLiquidaEbit": 0.72, "dividaBrutaPatrimonio": 0.74, "patrimonioAtivos": 0.36, "passivosAtivos": 0.64, "liquidezCorrente": 1.47, "valorDeMercado": 14304311000.0, "valorDeFirma": 15001822000.0, "patrimonioLiquido": 4713060000.0, "noTotalDePapeis": 586242000.0, "ativos": 13195348000.0, "ativoCirculante": 3471322000.0, "dividaBruta": 3464522000.0, "dividaLiquida": 697511000.0, "disponibilidade": 2767011000.0, "segmentoDeListagem": "Tradicional", "freeFloat": 0.4415, "tagAlong": 0, "liquidezMediaDiaria": 41978000.0, "setor": "Consumo C\u00edclico", "segmento": "Atividades Esportivas", "date": 1708204553.715275}