{"pL": -191.49, "pReceita(psr)": 21.04, "pVp": -21.7, "dividendYieldToyb3": 0.0, "payout": 0.0, "margemLiquida": -0.1099, "margemBruta": 0.2417, "margemEbit": -0.1064, "margemEbitda": 0.0, "evEbit": -198.46, "pEbit": -197.79, "pAtivo": 17.62, "pCapgiro": -25.87, "pAtivoCircLiq": -51.92, "vpa": -0.46, "lpa": -0.05, "giroAtivos": 0.84, "roe": -0.1133, "roic": 0.1185, "roa": -0.092, "dividaLiquidaPatrimonio": -0.07, "dividaLiquidaEbit": -0.67, "dividaBrutaPatrimonio": -0.07, "patrimonioAtivos": -0.81, "passivosAtivos": 1.81, "liquidezCorrente": 0.49, "cagrReceitas5Anos": 0.0, "valorDeMercado": 300639000.0, "valorDeFirma": 301659000.0, "patrimonioLiquido": -13852000.0, "noTotalDePapeis": 30063000.0, "ativos": 17060000.0, "ativoCirculante": 11270000.0, "dividaBruta": 1020000.0, "dividaLiquida": 1020000.0, "disponibilidade": "R$ -", "segmentoDeListagem": "Tradicional", "freeFloat": 0.0417, "tagAlong": 0, "setor": "Consumo C\u00edclico", "segmento": "Brinquedos e Jogos", "date": 1708202705.79752}