{"pL": 27.27, "pReceita(psr)": 4.43, "pVp": 8.76, "dividendYieldWege3": 0.0177, "payout": 0.4986, "margemLiquida": 0.1623, "margemBruta": 0.3236, "margemEbit": 0.1944, "margemEbitda": 0.2137, "evEbitda": 20.29, "evEbit": 22.3, "pEbitda": 20.71, "pEbit": 22.76, "pAtivo": 4.7, "pCapgiro": 14.69, "pAtivoCircLiq": -15.14, "vpa": 3.84, "lpa": 1.23, "giroAtivos": 1.06, "roe": 0.3213, "roic": 0.2722, "roa": 0.1762, "dividaLiquidaPatrimonio": -0.18, "dividaLiquidaEbitda": -0.42, "dividaLiquidaEbit": -0.46, "dividaBrutaPatrimonio": 0.18, "patrimonioAtivos": 0.54, "passivosAtivos": 0.45, "liquidezCorrente": 1.86, "cagrReceitas5Anos": 0.2167, "cagrLucros5Anos": 0.3157, "valorDeMercado": "R$ 141.281.723.000", "valorDeFirma": "R$ 138.406.985.000", "patrimonioLiquido": "R$ 16.123.041.000", "noTotalDePapeis": 4197317000.0, "ativos": "R$ 30.075.811.000", "ativoCirculante": "R$ 20.745.864.000", "dividaBruta": "R$ 2.848.572.000", "dividaLiquida": "R$ -2.874.738.000", "disponibilidade": "R$ 5.723.310.000", "segmentoDeListagem": "Novo Mercado", "freeFloat": 0.353, "tagAlong": 1.0, "liquidezMediaDiaria": "R$ 562.300.000", "setor": "Bens Industriais", "segmento": "Motores, Compressores e Outros"}